bar_tender_api/__init__.py
bar_tender_api/bar_tender_api.py
bar_tender_api/print_dll/Seagull.BarTender.Print.dll
bar_tender_api-1.0.0.dist-info/METADATA
bar_tender_api-1.0.0.dist-info/WHEEL
bar_tender_api-1.0.0.dist-info/RECORD
