Metadata-Version: 2.3
Name: bar-tender-api
Version: 1.0.0
Summary: BarTender 接口封装
Author: LiuWei
Author-email: 183074632@qq.com
Requires-Python: >=3.11,<3.14
Classifier: Programming Language :: Python :: 3
Classifier: Programming Language :: Python :: 3.11
Classifier: Programming Language :: Python :: 3.12
Classifier: Programming Language :: Python :: 3.13
Requires-Dist: pythonnet (>=3.0.5,<4.0.0)
